disjoint_set/__init__.py
disjoint_set/disjoint_set.py
disjoint_set_struct-0.0.1.dist-info/LICENSE
disjoint_set_struct-0.0.1.dist-info/METADATA
disjoint_set_struct-0.0.1.dist-info/WHEEL
disjoint_set_struct-0.0.1.dist-info/top_level.txt
disjoint_set_struct-0.0.1.dist-info/RECORD
