Metadata-Version: 2.2
Name: disjoint-set-struct
Version: 0.0.1
Summary: Implementation of disjoint set data structure (aka union-find data structure)
Author-email: Mary Drobotun <marydrobotun@gmail.com>
Project-URL: Homepage, https://github.com/marydrobotun/disjoint_set
Project-URL: Issues, https://github.com/marydrobotun/disjoint_set/issues
Classifier: Programming Language :: Python :: 3
Classifier: Operating System :: OS Independent
Requires-Python: >=3.8
License-File: LICENSE
